rest_authtoken/__init__.py
rest_authtoken/admin.py
rest_authtoken/apps.py
rest_authtoken/auth.py
rest_authtoken/email_confirmation.py
rest_authtoken/models.py
rest_authtoken/serializers.py
rest_authtoken/settings.py
rest_authtoken/tests.py
rest_authtoken/urls.py
rest_authtoken/views.py
rest_authtoken/management/__init__.py
rest_authtoken/management/commands/__init__.py
rest_authtoken/management/commands/clearexpiredauthtokens.py
rest_authtoken/migrations/0001_initial.py
rest_authtoken/migrations/0002_auto_20200822_1320.py
rest_authtoken/migrations/__init__.py
django_rest_authtoken-2.1.4.dist-info/LICENSE
django_rest_authtoken-2.1.4.dist-info/METADATA
django_rest_authtoken-2.1.4.dist-info/WHEEL
django_rest_authtoken-2.1.4.dist-info/top_level.txt
django_rest_authtoken-2.1.4.dist-info/RECORD
