Metadata-Version: 2.1
Name: django-rest-authtoken
Version: 2.1.4
Summary: A simple token-based auth backend for Django Rest Framework storing cryptographically hashed tokens on server-side.
Home-page: https://github.com/wichmannpas/django-rest-authtoken
Author: Pascal Wichmann
Author-email: wichmannpas@gmail.com
License: UNKNOWN
Platform: UNKNOWN
Classifier: Programming Language :: Python :: 3
Classifier: License :: OSI Approved :: Apache Software License
Classifier: Operating System :: OS Independent
